python_package_template/__init__.py
python_package_template/__main__.py
python_package_template/cli.py
python_package_template/main.py
python_package_template/py.typed
python_package_template_pypi-0.2.3.dist-info/METADATA
python_package_template_pypi-0.2.3.dist-info/WHEEL
python_package_template_pypi-0.2.3.dist-info/entry_points.txt
python_package_template_pypi-0.2.3.dist-info/licenses/LICENSE
python_package_template_pypi-0.2.3.dist-info/RECORD
