Metadata-Version: 2.4
Name: python-package-template-pypi
Version: 0.2.3
Summary: A GitHub template with my python package configurations.
Project-URL: Documentation, https://python-package-template-pypi.readthedocs.io/en/latest/
Project-URL: Homepage, https://pythonvilag.hu/
Project-URL: Issues, https://github.com/daniel-mizsak/python-package-template/issues
Project-URL: Repository, https://github.com/daniel-mizsak/python-package-template
Author-email: Daniel Mizsak <info@pythonvilag.hu>
License: MIT License
License-File: LICENSE
Keywords: github,package,pypi,python,template
Classifier: License :: OSI Approved :: MIT License
Classifier: Programming Language :: Python :: 3 :: Only
Classifier: Programming Language :: Python :: 3.11
Classifier: Programming Language :: Python :: 3.12
Requires-Python: >=3.11
Requires-Dist: numpy
Provides-Extra: dev
Requires-Dist: mypy; extra == 'dev'
Requires-Dist: pre-commit; extra == 'dev'
Requires-Dist: pytest; extra == 'dev'
Requires-Dist: pytest-cov; extra == 'dev'
Requires-Dist: ruff; extra == 'dev'
Requires-Dist: tox; extra == 'dev'
Provides-Extra: docs
Requires-Dist: furo; extra == 'docs'
Requires-Dist: sphinx; extra == 'docs'
Requires-Dist: sphinx-copybutton; extra == 'docs'
